LICENSE
MANIFEST.in
README.md
setup.py
monolith_filemanager/__init__.py
monolith_filemanager/errors.py
monolith_filemanager/path.py
monolith_filemanager/singleton.py
monolith_filemanager/version.py
monolith_filemanager.egg-info/PKG-INFO
monolith_filemanager.egg-info/SOURCES.txt
monolith_filemanager.egg-info/dependency_links.txt
monolith_filemanager.egg-info/entry_points.txt
monolith_filemanager.egg-info/requires.txt
monolith_filemanager.egg-info/top_level.txt
monolith_filemanager/adapters/__init__.py
monolith_filemanager/adapters/base.py
monolith_filemanager/adapters/errors.py
monolith_filemanager/adapters/local_file_processes.py
monolith_filemanager/adapters/s3_processes.py
monolith_filemanager/adapters/utils.py
monolith_filemanager/adapters/version_identifier.py
monolith_filemanager/components/__init__.py
monolith_filemanager/components/path_map.py
monolith_filemanager/console_commands/__init__.py
monolith_filemanager/console_commands/hello.py
monolith_filemanager/console_commands/install_boto.py
monolith_filemanager/console_commands/install_flask.py
monolith_filemanager/console_commands/install_tensorflow.py
monolith_filemanager/file/__init__.py
monolith_filemanager/file/base.py
monolith_filemanager/file/errors.py
monolith_filemanager/file/hdf5_file.py
monolith_filemanager/file/joblib_file.py
monolith_filemanager/file/json_file.py
monolith_filemanager/file/keras_model_file.py
monolith_filemanager/file/matlab.py
monolith_filemanager/file/numpy_file.py
monolith_filemanager/file/pandas_file.py
monolith_filemanager/file/protobuf_file.py
monolith_filemanager/file/standard_pickle_file.py
monolith_filemanager/file/stl_object_file.py
monolith_filemanager/file/vtk_file.py
monolith_filemanager/file/yml_file.py
monolith_filemanager/s3storage/__init__.py
monolith_filemanager/s3storage/bucket_manager.py
monolith_filemanager/s3storage/errors.py
monolith_filemanager/s3storage/file_manager.py
tests/adapters/__init__.py
tests/adapters/test_local_adapter.py
tests/adapters/test_s3_adapter.py
tests/adapters/test_utils.py
tests/adapters/test_version_identifier.py
tests/components/__init__.py
tests/components/test_path_map.py
tests/file/__init__.py
tests/file/test_base.py
tests/file/test_hdf5.py
tests/file/test_joblib_file.py
