Metadata-Version: 2.1
Name: monolith-filemanager
Version: 3.0.0
Summary: Python package for reading and writing files
Home-page: https://github.com/MonolithAILtd/monolith-filemanager
Author: Monolith AI
License: UNKNOWN
Platform: UNKNOWN
Classifier: Development Status :: 4 - Beta
Classifier: Programming Language :: Python :: 3
Classifier: Operating System :: OS Independent
Requires-Python: >=3.8
Provides-Extra: flask
Provides-Extra: 3d
Provides-Extra: matlab
